estare/__init__.py
estare/__main__.py
estare/src/__init__.py
estare/src/align.py
estare/src/image.py
estare/src/init.py
estare/src/modes.py
estare/src/rotate.py
estare/src/stack.py
estare/src/train.py
tests/__init__.py
tests/estare_tests.py
tests/reference_markers.py
tests/test_align.py
estare-1.0.0.dist-info/LICENSE
estare-1.0.0.dist-info/METADATA
estare-1.0.0.dist-info/WHEEL
estare-1.0.0.dist-info/entry_points.txt
estare-1.0.0.dist-info/top_level.txt
estare-1.0.0.dist-info/RECORD
