Metadata-Version: 2.1
Name: estare
Version: 1.0.0
Summary: Package for image alignment and stacking which can be used from the linux command-line
Home-page: https://github.com/soheil-soltani/estare
Author: Soheil Soltani
License: UNKNOWN
Platform: UNKNOWN
Classifier: Programming Language :: Python :: 3
Classifier: License :: OSI Approved :: GNU General Public License v3 (GPLv3)
Classifier: Operating System :: POSIX :: Linux
Requires-Python: >=3.6
License-File: LICENSE
Requires-Dist: numpy (>=1.19.2)
Requires-Dist: matplotlib (>=3.3.2)
Requires-Dist: scikit-image (>=0.17.2)
